apicheckr/__init__.py
apicheckr/apicheckr.py.tmpl
apicheckr-0.0.1.dev3.dist-info/DESCRIPTION.rst
apicheckr-0.0.1.dev3.dist-info/METADATA
apicheckr-0.0.1.dev3.dist-info/RECORD
apicheckr-0.0.1.dev3.dist-info/WHEEL
apicheckr-0.0.1.dev3.dist-info/entry_points.txt
apicheckr-0.0.1.dev3.dist-info/metadata.json
apicheckr-0.0.1.dev3.dist-info/top_level.txt
apicheckr-0.0.1.dev3.dist-info/zip-safe
