Metadata-Version: 2.0
Name: apicheckr
Version: 0.0.1.dev3
Summary: generate unittest test cases for OpenAPI v2
Home-page: https://www.fotopuzzle.de/
Author: puzzle & play GmbH
Author-email: apicheckr@puzzleandplay.de
License: AGPLv3
Platform: any
Requires-Dist: bravado
Requires-Dist: bravado-core
Requires-Dist: Jinja2
